bandit_gym-0.1.0.dist-info/licenses/LICENSE
bandit_gym_rishi/__init__.py
bandit_gym_rishi/bandit_env.py
bandit_gym-0.1.0.dist-info/METADATA
bandit_gym-0.1.0.dist-info/WHEEL
bandit_gym-0.1.0.dist-info/top_level.txt
bandit_gym-0.1.0.dist-info/RECORD
