Metadata-Version: 2.4
Name: bandit-gym
Version: 0.1.0
Summary: A Gym-compatible Multi-Armed Bandit simulator.
Author-email: Rishi Vora <Vorarishi04@gmail.com>
License: MIT License
Requires-Python: >=3.7
License-File: LICENSE
Requires-Dist: gym
Requires-Dist: numpy
Dynamic: license-file
